gammarer/aws_ec2_auto_scaling_instance_running_scheduler/__init__.py
gammarer/aws_ec2_auto_scaling_instance_running_scheduler/py.typed
gammarer/aws_ec2_auto_scaling_instance_running_scheduler/_jsii/__init__.py
gammarer/aws_ec2_auto_scaling_instance_running_scheduler/_jsii/aws-ec2-auto-scaling-instance-running-scheduler@1.1.16.jsii.tgz
gammarer.aws_ec2_auto_scaling_instance_running_scheduler-1.1.16.dist-info/LICENSE
gammarer.aws_ec2_auto_scaling_instance_running_scheduler-1.1.16.dist-info/METADATA
gammarer.aws_ec2_auto_scaling_instance_running_scheduler-1.1.16.dist-info/WHEEL
gammarer.aws_ec2_auto_scaling_instance_running_scheduler-1.1.16.dist-info/top_level.txt
gammarer.aws_ec2_auto_scaling_instance_running_scheduler-1.1.16.dist-info/RECORD
